lab07/lab07/counter_divider.v
`timescale 1ns / 1ps

module counter_divider(
    input clk,
    input reset,
    output reg [3:0] count,
    output reg slow_clk
);
    always @(posedge clk or posedge reset) begin
        if (reset) begin
            count <= 4'd0;
            slow_clk <= 1'b0;
        end else if (count == 4'd7) begin
            count <= 4'd0;
            slow_clk <= ~slow_clk;
        end else begin
            count <= count + 4'd1;
        end
    end
endmodule

lab07/lab07/tb_counter_divider.v
`timescale 1ns / 1ps

module tb_counter_divider;
    reg clk;
    reg reset;
    wire [3:0] count;
    wire slow_clk;

    counter_divider uut (.clk(clk), .reset(reset), .count(count), .slow_clk(slow_clk));

    initial begin
        clk = 1'b0;
        forever #5 clk = ~clk;
    end

    initial begin
        $dumpfile("lab07_counter_divider.vcd");
        $dumpvars(0, tb_counter_divider);

        reset = 1'b1;
        #12;
        reset = 1'b0;
        #220;

        reset = 1'b1;
        #10;
        reset = 1'b0;
        #300;

        $finish;
    end
endmodule

lab07/lab07/lab07_counter_divider.vcd
$date
	Thu Jul 16 00:26:33 2026
$end
$version
	Icarus Verilog
$end
$timescale
	1ps
$end
$scope module tb_counter_divider $end
$var wire 1 ! slow_clk $end
$var wire 4 " count [3:0] $end
$var reg 1 # clk $end
$var reg 1 $ reset $end
$scope module uut $end
$var wire 1 # clk $end
$var wire 1 $ reset $end
$var reg 4 % count [3:0] $end
$var reg 1 ! slow_clk $end
$upscope $end
$upscope $end
$enddefinitions $end
$comment Show the parameter values. $end
$dumpall
$end
#0
$dumpvars
b0 %
1$
0#
b0 "
0!
$end
#5000
1#
#10000
0#
#12000
0$
#15000
b1 "
b1 %
1#
#20000
0#
#25000
b10 "
b10 %
1#
#30000
0#
#35000
b11 "
b11 %
1#
#40000
0#
#45000
b100 "
b100 %
1#
#50000
0#
#55000
b101 "
b101 %
1#
#60000
0#
#65000
b110 "
b110 %
1#
#70000
0#
#75000
b111 "
b111 %
1#
#80000
0#
#85000
1!
b0 "
b0 %
1#
#90000
0#
#95000
b1 "
b1 %
1#
#100000
0#
#105000
b10 "
b10 %
1#
#110000
0#
#115000
b11 "
b11 %
1#
#120000
0#
#125000
b100 "
b100 %
1#
#130000
0#
#135000
b101 "
b101 %
1#
#140000
0#
#145000
b110 "
b110 %
1#
#150000
0#
#155000
b111 "
b111 %
1#
#160000
0#
#165000
0!
b0 "
b0 %
1#
#170000
0#
#175000
b1 "
b1 %
1#
#180000
0#
#185000
b10 "
b10 %
1#
#190000
0#
#195000
b11 "
b11 %
1#
#200000
0#
#205000
b100 "
b100 %
1#
#210000
0#
#215000
b101 "
b101 %
1#
#220000
0#
#225000
b110 "
b110 %
1#
#230000
0#
#232000
b0 "
b0 %
1$
#235000
1#
#240000
0#
#242000
0$
#245000
b1 "
b1 %
1#
#250000
0#
#255000
b10 "
b10 %
1#
#260000
0#
#265000
b11 "
b11 %
1#
#270000
0#
#275000
b100 "
b100 %
1#
#280000
0#
#285000
b101 "
b101 %
1#
#290000
0#
#295000
b110 "
b110 %
1#
#300000
0#
#305000
b111 "
b111 %
1#
#310000
0#
#315000
1!
b0 "
b0 %
1#
#320000
0#
#325000
b1 "
b1 %
1#
#330000
0#
#335000
b10 "
b10 %
1#
#340000
0#
#345000
b11 "
b11 %
1#
#350000
0#
#355000
b100 "
b100 %
1#
#360000
0#
#365000
b101 "
b101 %
1#
#370000
0#
#375000
b110 "
b110 %
1#
#380000
0#
#385000
b111 "
b111 %
1#
#390000
0#
#395000
0!
b0 "
b0 %
1#
#400000
0#
#405000
b1 "
b1 %
1#
#410000
0#
#415000
b10 "
b10 %
1#
#420000
0#
#425000
b11 "
b11 %
1#
#430000
0#
#435000
b100 "
b100 %
1#
#440000
0#
#445000
b101 "
b101 %
1#
#450000
0#
#455000
b110 "
b110 %
1#
#460000
0#
#465000
b111 "
b111 %
1#
#470000
0#
#475000
1!
b0 "
b0 %
1#
#480000
0#
#485000
b1 "
b1 %
1#
#490000
0#
#495000
b10 "
b10 %
1#
#500000
0#
#505000
b11 "
b11 %
1#
#510000
0#
#515000
b100 "
b100 %
1#
#520000
0#
#525000
b101 "
b101 %
1#
#530000
0#
#535000
b110 "
b110 %
1#
