lab04/lab04/mux_decoder.v
`timescale 1ns / 1ps

module mux4to1(
    input [3:0] data,
    input [1:0] sel,
    output reg y
);
    always @(*) begin
        case (sel)
            2'b00: y = data[0];
            2'b01: y = data[1];
            2'b10: y = data[2];
            2'b11: y = data[3];
            default: y = 1'b0;
        endcase
    end
endmodule

module mux8to1(
    input [7:0] data,
    input [2:0] sel,
    output reg y
);
    always @(*) begin
        case (sel)
            3'b000: y = data[0];
            3'b001: y = data[1];
            3'b010: y = data[2];
            3'b011: y = data[3];
            3'b100: y = data[4];
            3'b101: y = data[5];
            3'b110: y = data[6];
            3'b111: y = data[7];
            default: y = 1'b0;
        endcase
    end
endmodule

module decoder2to4(
    input [1:0] sel,
    input enable,
    output reg [3:0] y
);
    always @(*) begin
        if (enable) begin
            case (sel)
                2'b00: y = 4'b0001;
                2'b01: y = 4'b0010;
                2'b10: y = 4'b0100;
                2'b11: y = 4'b1000;
                default: y = 4'b0000;
            endcase
        end else begin
            y = 4'b0000;
        end
    end
endmodule

lab04/lab04/tb_mux_decoder.v
`timescale 1ns / 1ps

module tb_mux_decoder;
    reg [3:0] data;
    reg [7:0] data8;
    reg [1:0] sel;
    reg [2:0] sel8;
    reg enable;
    wire mux_y;
    wire mux8_y;
    wire [3:0] dec_y;

    integer i;

    mux4to1 mux (.data(data), .sel(sel), .y(mux_y));
    mux8to1 mux8 (.data(data8), .sel(sel8), .y(mux8_y));
    decoder2to4 dec (.sel(sel), .enable(enable), .y(dec_y));

    initial begin
        $dumpfile("lab04_mux_decoder.vcd");
        $dumpvars(0, tb_mux_decoder);

        data = 4'b1010;
        enable = 1'b1;

        $display("data sel enable | mux_y dec_y");
        for (i = 0; i < 4; i = i + 1) begin
            sel = i[1:0];
            #10;
            $display("%b  %b    %b    |   %b   %b", data, sel, enable, mux_y, dec_y);
        end

        enable = 1'b0;
        for (i = 0; i < 4; i = i + 1) begin
            sel = i[1:0];
            #10;
            $display("%b  %b    %b    |   %b   %b", data, sel, enable, mux_y, dec_y);
        end

        data8 = 8'b1011_0010;
        $display("");
        $display("data8    sel8 | mux8_y");
        for (i = 0; i < 8; i = i + 1) begin
            sel8 = i[2:0];
            #10;
            $display("%b  %b  |   %b", data8, sel8, mux8_y);
        end

        $finish;
    end
endmodule

lab04/lab04/lab04_mux_decoder.vcd
$date
	Thu Jul 09 21:42:41 2026
$end
$version
	Icarus Verilog
$end
$timescale
	1ps
$end
$scope module tb_mux_decoder $end
$var wire 1 ! mux_y $end
$var wire 1 " mux8_y $end
$var wire 4 # dec_y [3:0] $end
$var reg 4 $ data [3:0] $end
$var reg 8 % data8 [7:0] $end
$var reg 1 & enable $end
$var reg 2 ' sel [1:0] $end
$var reg 3 ( sel8 [2:0] $end
$var integer 32 ) i [31:0] $end
$scope module dec $end
$var wire 1 & enable $end
$var wire 2 * sel [1:0] $end
$var reg 4 + y [3:0] $end
$upscope $end
$scope module mux $end
$var wire 4 , data [3:0] $end
$var wire 2 - sel [1:0] $end
$var reg 1 ! y $end
$upscope $end
$scope module mux8 $end
$var wire 8 . data [7:0] $end
$var wire 3 / sel [2:0] $end
$var reg 1 " y $end
$upscope $end
$upscope $end
$enddefinitions $end
$comment Show the parameter values. $end
$dumpall
$end
#0
$dumpvars
bx /
bx .
b0 -
b1010 ,
b1 +
b0 *
b0 )
bx (
b0 '
1&
bx %
b1010 $
b1 #
x"
0!
$end
#10000
b10 #
b10 +
1!
b1 '
b1 *
b1 -
b1 )
#20000
b100 #
b100 +
0!
b10 '
b10 *
b10 -
b10 )
#30000
b1000 #
b1000 +
1!
b11 '
b11 *
b11 -
b11 )
#40000
0!
b0 #
b0 +
b0 '
b0 *
b0 -
0&
b0 )
#50000
1!
b1 '
b1 *
b1 -
b1 )
#60000
0!
b10 '
b10 *
b10 -
b10 )
#70000
1!
b11 '
b11 *
b11 -
b11 )
#80000
0"
b0 (
b0 /
b10110010 %
b10110010 .
b0 )
#90000
1"
b1 (
b1 /
b1 )
#100000
0"
b10 (
b10 /
b10 )
#110000
b11 (
b11 /
b11 )
#120000
1"
b100 (
b100 /
b100 )
#130000
b101 (
b101 /
b101 )
#140000
0"
b110 (
b110 /
b110 )
#150000
1"
b111 (
b111 /
b111 )
#160000
b1000 )
