lab07/lab07/lab08/lab08/shift_register.v
`timescale 1ns / 1ps

module shift_register4(
    input clk,
    input reset,
    input load,
    input direction,
    input serial_in,
    input [3:0] parallel_in,
    output reg [3:0] q,
    output serial_out
);
    assign serial_out = direction ? q[3] : q[0];

    always @(posedge clk or posedge reset) begin
        if (reset) begin
            q <= 4'b0000;
        end else if (load) begin
            q <= parallel_in;
        end else if (direction) begin
            q <= {q[2:0], serial_in};
        end else begin
            q <= {serial_in, q[3:1]};
        end
    end
endmodule

lab08/lab08/tb_shift_register.v
`timescale 1ns / 1ps

module tb_shift_register;
    reg clk;
    reg reset;
    reg load;
    reg direction;
    reg serial_in;
    reg [3:0] parallel_in;
    wire [3:0] q;
    wire serial_out;

    shift_register4 uut (
        .clk(clk),
        .reset(reset),
        .load(load),
        .direction(direction),
        .serial_in(serial_in),
        .parallel_in(parallel_in),
        .q(q),
        .serial_out(serial_out)
    );

    initial begin
        clk = 1'b0;
        forever #5 clk = ~clk;
    end

    initial begin
        $dumpfile("lab08_shift_register.vcd");
        $dumpvars(0, tb_shift_register);

        reset = 1'b1;
        load = 1'b0;
        direction = 1'b0;
        serial_in = 1'b0;
        parallel_in = 4'b1011;
        #12;

        reset = 1'b0;
        load = 1'b1;
        #10;

        load = 1'b0;
        serial_in = 1'b1;
        #20;

        direction = 1'b1;
        serial_in = 1'b0;
        #20;

        serial_in = 1'b0;
        #20;

        serial_in = 1'b1;
        #20;

        $finish;
    end
endmodule

lab07/lab07/lab08/lab08/lab08_shift_register.vcd
$date
	Thu Jul 16 00:46:13 2026
$end
$version
	Icarus Verilog
$end
$timescale
	1ps
$end
$scope module tb_shift_register $end
$var wire 1 ! serial_out $end
$var wire 4 " q [3:0] $end
$var reg 1 # clk $end
$var reg 1 $ direction $end
$var reg 1 % load $end
$var reg 4 & parallel_in [3:0] $end
$var reg 1 ' reset $end
$var reg 1 ( serial_in $end
$scope module uut $end
$var wire 1 # clk $end
$var wire 1 $ direction $end
$var wire 1 % load $end
$var wire 4 ) parallel_in [3:0] $end
$var wire 1 ' reset $end
$var wire 1 ( serial_in $end
$var wire 1 ! serial_out $end
$var reg 4 * q [3:0] $end
$upscope $end
$upscope $end
$enddefinitions $end
$comment Show the parameter values. $end
$dumpall
$end
#0
$dumpvars
b0 *
b1011 )
0(
1'
b1011 &
0%
0$
0#
b0 "
0!
$end
#5000
1#
#10000
0#
#12000
1%
0'
#15000
1!
b1011 "
b1011 *
1#
#20000
0#
#22000
1(
0%
#25000
b1101 "
b1101 *
1#
#30000
0#
#35000
0!
b1110 "
b1110 *
1#
#40000
0#
#42000
1!
0(
1$
#45000
b1100 "
b1100 *
1#
#50000
0#
#55000
b1000 "
b1000 *
1#
#60000
0#
#65000
0!
b0 "
b0 *
1#
#70000
0#
#75000
1#
#80000
0#
#82000
1(
#85000
b1 "
b1 *
1#
#90000
0#
#95000
b11 "
b11 *
1#
