lab10/lab10/traffic_light_controller.v
`timescale 1ns / 1ps

module traffic_light_controller(
    input clk,
    input reset,
    input ped_request,
    output reg [2:0] main_light,
    output reg [2:0] side_light
);
    localparam RED = 3'b100;
    localparam YELLOW = 3'b010;
    localparam GREEN = 3'b001;

    localparam MAIN_GREEN = 2'd0;
    localparam MAIN_YELLOW = 2'd1;
    localparam SIDE_GREEN = 2'd2;
    localparam SIDE_YELLOW = 2'd3;

    localparam MAIN_GREEN_NORMAL_TICKS = 4'd6;
    localparam MAIN_GREEN_REQUEST_TICKS = 4'd3;
    localparam YELLOW_TICKS = 4'd2;
    localparam SIDE_GREEN_TICKS = 4'd4;

    reg [1:0] state;
    reg [3:0] timer;
    reg [3:0] limit;

    always @(*) begin
        case (state)
            MAIN_GREEN: begin
                main_light = GREEN;
                side_light = RED;
                limit = ped_request ? MAIN_GREEN_REQUEST_TICKS : MAIN_GREEN_NORMAL_TICKS;
            end
            MAIN_YELLOW: begin
                main_light = YELLOW;
                side_light = RED;
                limit = YELLOW_TICKS;
            end
            SIDE_GREEN: begin
                main_light = RED;
                side_light = GREEN;
                limit = SIDE_GREEN_TICKS;
            end
            SIDE_YELLOW: begin
                main_light = RED;
                side_light = YELLOW;
                limit = YELLOW_TICKS;
            end
            default: begin
                main_light = GREEN;
                side_light = RED;
                limit = MAIN_GREEN_NORMAL_TICKS;
            end
        endcase
    end

    always @(posedge clk or posedge reset) begin
        if (reset) begin
            state <= MAIN_GREEN;
            timer <= 4'd0;
        end else if (timer >= limit - 4'd1) begin
            timer <= 4'd0;
            case (state)
                MAIN_GREEN: state <= MAIN_YELLOW;
                MAIN_YELLOW: state <= SIDE_GREEN;
                SIDE_GREEN: state <= SIDE_YELLOW;
                SIDE_YELLOW: state <= MAIN_GREEN;
                default: state <= MAIN_GREEN;
            endcase
        end else begin
            timer <= timer + 4'd1;
        end
    end
endmodule

lab10/lab10/tb_traffic_light_controller.v
`timescale 1ns / 1ps

module tb_traffic_light_controller;
    reg clk;
    reg reset;
    reg ped_request;
    wire [2:0] main_light;
    wire [2:0] side_light;

    traffic_light_controller uut (
        .clk(clk),
        .reset(reset),
        .ped_request(ped_request),
        .main_light(main_light),
        .side_light(side_light)
    );

    initial begin
        clk = 1'b0;
        forever #5 clk = ~clk;
    end

    initial begin
        $dumpfile("lab10_traffic_light.vcd");
        $dumpvars(0, tb_traffic_light_controller);

        reset = 1'b1;
        ped_request = 1'b0;
        #12;

        reset = 1'b0;
        #90;

        ped_request = 1'b1;
        #40;

        ped_request = 1'b0;
        #100;

        reset = 1'b1;
        #10;
        reset = 1'b0;
        #40;

        $finish;
    end
endmodule

lab10/lab10/lab10_traffic_light.vcd
$date
	Sun May 17 22:59:28 2026
$end
$version
	Icarus Verilog
$end
$timescale
	1ps
$end
$scope module tb_traffic_light_controller $end
$var wire 3 ! side_light [2:0] $end
$var wire 3 " main_light [2:0] $end
$var reg 1 # clk $end
$var reg 1 $ ped_request $end
$var reg 1 % reset $end
$scope module uut $end
$var wire 1 # clk $end
$var wire 1 $ ped_request $end
$var wire 1 % reset $end
$var parameter 3 & GREEN $end
$var parameter 2 ' MAIN_GREEN $end
$var parameter 4 ( MAIN_GREEN_NORMAL_TICKS $end
$var parameter 4 ) MAIN_GREEN_REQUEST_TICKS $end
$var parameter 2 * MAIN_YELLOW $end
$var parameter 3 + RED $end
$var parameter 2 , SIDE_GREEN $end
$var parameter 4 - SIDE_GREEN_TICKS $end
$var parameter 2 . SIDE_YELLOW $end
$var parameter 3 / YELLOW $end
$var parameter 4 0 YELLOW_TICKS $end
$var reg 4 1 limit [3:0] $end
$var reg 3 2 main_light [2:0] $end
$var reg 3 3 side_light [2:0] $end
$var reg 2 4 state [1:0] $end
$var reg 4 5 timer [3:0] $end
$upscope $end
$upscope $end
$enddefinitions $end
$comment Show the parameter values. $end
$dumpall
b10 0
b10 /
b11 .
b100 -
b10 ,
b100 +
b1 *
b11 )
b110 (
b0 '
b1 &
$end
#0
$dumpvars
b0 5
b0 4
b100 3
b1 2
b110 1
1%
0$
0#
b1 "
b100 !
$end
#5000
1#
#10000
0#
#12000
0%
#15000
b1 5
1#
#20000
0#
#25000
b10 5
1#
#30000
0#
#35000
b11 5
1#
#40000
0#
#45000
b100 5
1#
#50000
0#
#55000
b101 5
1#
#60000
0#
#65000
b10 1
b10 "
b10 2
b1 4
b0 5
1#
#70000
0#
#75000
b1 5
1#
#80000
0#
#85000
b100 1
b1 !
b1 3
b100 "
b100 2
b10 4
b0 5
1#
#90000
0#
#95000
b1 5
1#
#100000
0#
#102000
1$
#105000
b10 5
1#
#110000
0#
#115000
b11 5
1#
#120000
0#
#125000
b10 1
b10 !
b10 3
b11 4
b0 5
1#
#130000
0#
#135000
b1 5
1#
#140000
0#
#142000
0$
#145000
b110 1
b100 !
b100 3
b1 "
b1 2
b0 4
b0 5
1#
#150000
0#
#155000
b1 5
1#
#160000
0#
#165000
b10 5
1#
#170000
0#
#175000
b11 5
1#
#180000
0#
#185000
b100 5
1#
#190000
0#
#195000
b101 5
1#
#200000
0#
#205000
b10 1
b10 "
b10 2
b1 4
b0 5
1#
#210000
0#
#215000
b1 5
1#
#220000
0#
#225000
b100 1
b1 !
b1 3
b100 "
b100 2
b10 4
b0 5
1#
#230000
0#
#235000
b1 5
1#
#240000
0#
#242000
b110 1
b100 !
b100 3
b1 "
b1 2
b0 5
b0 4
1%
#245000
1#
#250000
0#
#252000
0%
#255000
b1 5
1#
#260000
0#
#265000
b10 5
1#
#270000
0#
#275000
b11 5
1#
#280000
0#
#285000
b100 5
1#
