lab10/lab10/smart_school_zone_controller.v
`timescale 1ns / 1ps

module smart_school_zone_controller(
    input clk,
    input reset,
    input school_mode,
    input flash_mode,
    input ped_request,
    output reg [2:0] main_light,
    output reg [2:0] side_light,
    output reg walk_light,
    output reg [3:0] countdown
);
    localparam RED    = 3'b100;
    localparam YELLOW = 3'b010;
    localparam GREEN  = 3'b001;
    localparam OFF    = 3'b000;

    localparam S0_MAIN_GREEN  = 3'd0;
    localparam S1_MAIN_YELLOW = 3'd1;
    localparam S2_SIDE_GREEN  = 3'd2;
    localparam S3_SIDE_YELLOW = 3'd3;
    localparam S4_WALK        = 3'd4;

    localparam NORMAL_MAIN_GREEN_TICKS = 4'd10;
    localparam SCHOOL_MAIN_GREEN_TICKS = 4'd8;
    localparam NORMAL_SIDE_GREEN_TICKS = 4'd8;
    localparam SCHOOL_SIDE_GREEN_TICKS = 4'd10;
    localparam YELLOW_TICKS            = 4'd3;
    localparam NORMAL_WALK_SECONDS     = 4'd5;
    localparam SCHOOL_WALK_SECONDS     = 4'd8;

    reg [2:0] state;
    reg [3:0] timer;
    reg [3:0] limit;
    reg ped_pending;
    reg flash_toggle;

    wire flash_active = flash_mode && !school_mode;
    wire [3:0] walk_seconds = school_mode ? SCHOOL_WALK_SECONDS : NORMAL_WALK_SECONDS;

    always @(*) begin
        limit = NORMAL_MAIN_GREEN_TICKS;
        countdown = 4'd0;

        if (flash_active) begin
            main_light = flash_toggle ? YELLOW : OFF;
            side_light = RED;
            walk_light = 1'b0;
        end else begin
            case (state)
                S0_MAIN_GREEN: begin
                    main_light = GREEN;
                    side_light = RED;
                    walk_light = 1'b0;
                    limit = school_mode ? SCHOOL_MAIN_GREEN_TICKS : NORMAL_MAIN_GREEN_TICKS;
                end

                S1_MAIN_YELLOW: begin
                    main_light = YELLOW;
                    side_light = RED;
                    walk_light = 1'b0;
                    limit = YELLOW_TICKS;
                end

                S2_SIDE_GREEN: begin
                    main_light = RED;
                    side_light = GREEN;
                    walk_light = 1'b0;
                    limit = school_mode ? SCHOOL_SIDE_GREEN_TICKS : NORMAL_SIDE_GREEN_TICKS;
                end

                S3_SIDE_YELLOW: begin
                    main_light = RED;
                    side_light = YELLOW;
                    walk_light = 1'b0;
                    limit = YELLOW_TICKS;
                end

                S4_WALK: begin
                    main_light = RED;
                    side_light = RED;
                    walk_light = 1'b1;
                    limit = walk_seconds + 4'd1;
                    countdown = (timer <= walk_seconds) ? (walk_seconds - timer) : 4'd0;
                end

                default: begin
                    main_light = GREEN;
                    side_light = RED;
                    walk_light = 1'b0;
                    limit = school_mode ? SCHOOL_MAIN_GREEN_TICKS : NORMAL_MAIN_GREEN_TICKS;
                end
            endcase
        end
    end

    always @(posedge clk or posedge reset) begin
        if (reset) begin
            state <= S0_MAIN_GREEN;
            timer <= 4'd0;
            ped_pending <= 1'b0;
            flash_toggle <= 1'b1;
        end else if (flash_active) begin
            state <= S0_MAIN_GREEN;
            timer <= 4'd0;
            ped_pending <= 1'b0;
            flash_toggle <= ~flash_toggle;
        end else begin
            flash_toggle <= 1'b1;

            if (ped_request && (state != S4_WALK)) begin
                ped_pending <= 1'b1;
            end

            if (timer >= limit - 4'd1) begin
                timer <= 4'd0;

                case (state)
                    S0_MAIN_GREEN: begin
                        state <= S1_MAIN_YELLOW;
                    end

                    S1_MAIN_YELLOW: begin
                        state <= S2_SIDE_GREEN;
                    end

                    S2_SIDE_GREEN: begin
                        if (ped_pending || ped_request) begin
                            state <= S4_WALK;
                            ped_pending <= 1'b0;
                        end else begin
                            state <= S3_SIDE_YELLOW;
                        end
                    end

                    S4_WALK: begin
                        state <= S3_SIDE_YELLOW;
                    end

                    S3_SIDE_YELLOW: begin
                        state <= S0_MAIN_GREEN;
                    end

                    default: begin
                        state <= S0_MAIN_GREEN;
                    end
                endcase
            end else begin
                timer <= timer + 4'd1;
            end
        end
    end
endmodule

lab10/lab10/tb_smart_school_zone_controller.v
`timescale 1ns / 1ps

module tb_smart_school_zone_controller;
    reg clk;
    reg reset;
    reg school_mode;
    reg flash_mode;
    reg ped_request;

    wire [2:0] main_light;
    wire [2:0] side_light;
    wire walk_light;
    wire [3:0] countdown;

    localparam RED    = 3'b100;
    localparam YELLOW = 3'b010;
    localparam GREEN  = 3'b001;
    localparam OFF    = 3'b000;

    integer errors;
    integer tick_count;

    smart_school_zone_controller uut (
        .clk(clk),
        .reset(reset),
        .school_mode(school_mode),
        .flash_mode(flash_mode),
        .ped_request(ped_request),
        .main_light(main_light),
        .side_light(side_light),
        .walk_light(walk_light),
        .countdown(countdown)
    );

    initial begin
        clk = 1'b0;
        forever #5 clk = ~clk;
    end

    task check;
        input condition;
        input [1023:0] message;
        begin
            if (condition) begin
                $display("PASS: %0s", message);
            end else begin
                $display("FAIL: %0s at time %0t", message, $time);
                errors = errors + 1;
            end
        end
    endtask

    task check_safe;
        begin
            check(!(main_light == GREEN && side_light == GREEN),
                  "main and side roads are never green at the same time");
            check((walk_light == 1'b0) || (main_light == RED && side_light == RED),
                  "walk light is active only when both roads are red");
        end
    endtask

    task wait_tick;
        begin
            @(posedge clk);
            #1;
            check_safe();
        end
    endtask

    task wait_ticks;
        input integer n;
        begin
            for (tick_count = 0; tick_count < n; tick_count = tick_count + 1) begin
                wait_tick();
            end
        end
    endtask

    task wait_for_walk;
        begin
            while (walk_light != 1'b1) begin
                wait_tick();
            end
        end
    endtask

    task expect_lights;
        input [2:0] expected_main;
        input [2:0] expected_side;
        input expected_walk;
        input [3:0] expected_countdown;
        input [1023:0] message;
        begin
            check(main_light == expected_main, {message, " main light"});
            check(side_light == expected_side, {message, " side light"});
            check(walk_light == expected_walk, {message, " walk light"});
            check(countdown == expected_countdown, {message, " countdown"});
        end
    endtask

    initial begin
        $dumpfile("smart_school_zone.vcd");
        $dumpvars(0, tb_smart_school_zone_controller);

        errors = 0;
        reset = 1'b1;
        school_mode = 1'b0;
        flash_mode = 1'b0;
        ped_request = 1'b0;

        $display("=== Scenario 1: Reset operation ===");
        #2;
        expect_lights(GREEN, RED, 1'b0, 4'd0, "reset returns to safe main green state");
        reset = 1'b0;
        wait_tick();

        $display("=== Scenario 2: Normal traffic cycle ===");
        expect_lights(GREEN, RED, 1'b0, 4'd0, "normal mode starts with main green");
        wait_ticks(9);
        expect_lights(YELLOW, RED, 1'b0, 4'd0, "normal mode reaches main yellow after 10 ticks");
        wait_ticks(3);
        expect_lights(RED, GREEN, 1'b0, 4'd0, "normal mode reaches side green after yellow");
        wait_ticks(8);
        expect_lights(RED, YELLOW, 1'b0, 4'd0, "normal mode skips walk without pedestrian request");
        wait_ticks(3);
        expect_lights(GREEN, RED, 1'b0, 4'd0, "normal mode returns to main green");

        $display("=== Scenario 3: School mode timing ===");
        school_mode = 1'b1;
        wait_tick();
        expect_lights(GREEN, RED, 1'b0, 4'd0, "school mode main green is active");
        wait_ticks(7);
        expect_lights(YELLOW, RED, 1'b0, 4'd0, "school mode shortens main green to 8 ticks");
        wait_ticks(3);
        expect_lights(RED, GREEN, 1'b0, 4'd0, "school mode enters side green");
        wait_ticks(10);
        expect_lights(RED, YELLOW, 1'b0, 4'd0, "school mode extends side green to 10 ticks");
        wait_ticks(3);
        expect_lights(GREEN, RED, 1'b0, 4'd0, "school mode cycle returns to main green");

        $display("=== Scenario 4: Flashing yellow mode ===");
        school_mode = 1'b0;
        flash_mode = 1'b1;
        wait_tick();
        check(side_light == RED, "flashing mode keeps side road red");
        check(main_light == YELLOW || main_light == OFF, "flashing mode drives main road yellow/off");
        wait_tick();
        check(side_light == RED, "flashing mode continues to keep side road red");
        check(main_light == YELLOW || main_light == OFF, "flashing mode continues yellow/off flashing");
        flash_mode = 1'b0;
        wait_tick();
        expect_lights(GREEN, RED, 1'b0, 4'd0, "leaving flashing mode returns to safe main green");

        $display("=== Scenario 5: Pedestrian request and walk countdown ===");
        school_mode = 1'b1;
        ped_request = 1'b1;
        wait_tick();
        ped_request = 1'b0;
        wait_ticks(7);
        expect_lights(YELLOW, RED, 1'b0, 4'd0, "pedestrian request waits through main yellow");
        wait_ticks(3);
        expect_lights(RED, GREEN, 1'b0, 4'd0, "pedestrian request waits through side green");
        wait_for_walk();
        expect_lights(RED, RED, 1'b1, 4'd8, "school walk starts with countdown 8");
        wait_tick();
        expect_lights(RED, RED, 1'b1, 4'd7, "school walk countdown 7");
        wait_tick();
        expect_lights(RED, RED, 1'b1, 4'd6, "school walk countdown 6");
        wait_tick();
        expect_lights(RED, RED, 1'b1, 4'd5, "school walk countdown 5");
        wait_tick();
        expect_lights(RED, RED, 1'b1, 4'd4, "school walk countdown 4");
        wait_tick();
        expect_lights(RED, RED, 1'b1, 4'd3, "school walk countdown 3");
        wait_tick();
        expect_lights(RED, RED, 1'b1, 4'd2, "school walk countdown 2");
        wait_tick();
        expect_lights(RED, RED, 1'b1, 4'd1, "school walk countdown 1");
        wait_tick();
        expect_lights(RED, RED, 1'b1, 4'd0, "school walk countdown 0");
        wait_tick();
        expect_lights(RED, YELLOW, 1'b0, 4'd0, "walk state exits to side yellow");

        $display("=== Scenario 6: Reset during Side Green edge case ===");
        wait_ticks(3);
        school_mode = 1'b0;
        wait_ticks(10);
        wait_ticks(3);
        expect_lights(RED, GREEN, 1'b0, 4'd0, "controller is in side green before edge reset");
        reset = 1'b1;
        #2;
        expect_lights(GREEN, RED, 1'b0, 4'd0, "reset during side green immediately returns safe state");
        reset = 1'b0;
        wait_tick();

        $display("=== Scenario 7: Multiple pedestrian requests while served ===");
        school_mode = 1'b1;
        ped_request = 1'b1;
        wait_tick();
        ped_request = 1'b0;
        wait_ticks(7);
        wait_ticks(3);
        wait_for_walk();
        expect_lights(RED, RED, 1'b1, 4'd8, "first request is being served");
        ped_request = 1'b1;
        wait_ticks(2);
        ped_request = 1'b0;
        wait_ticks(7);
        expect_lights(RED, YELLOW, 1'b0, 4'd0, "extra request during walk does not restart walk");
        wait_ticks(3);
        expect_lights(GREEN, RED, 1'b0, 4'd0, "controller returns to normal sequence after served request");

        if (errors == 0) begin
            $display("=== SIMULATION PASSED: all smart school-zone controller checks succeeded ===");
        end else begin
            $display("=== SIMULATION FAILED: %0d check(s) failed ===", errors);
        end

        $finish;
    end
endmodule

lab10/lab10/smart_school_zone.vcd
$date
	Tue Jul 21 10:52:24 2026
$end
$version
	Icarus Verilog
$end
$timescale
	1ps
$end
$scope module tb_smart_school_zone_controller $end
$var wire 1 ! walk_light $end
$var wire 3 " side_light [2:0] $end
$var wire 3 # main_light [2:0] $end
$var wire 4 $ countdown [3:0] $end
$var parameter 3 % GREEN $end
$var parameter 3 & OFF $end
$var parameter 3 ' RED $end
$var parameter 3 ( YELLOW $end
$var reg 1 ) clk $end
$var reg 1 * flash_mode $end
$var reg 1 + ped_request $end
$var reg 1 , reset $end
$var reg 1 - school_mode $end
$var integer 32 . errors [31:0] $end
$var integer 32 / tick_count [31:0] $end
$scope module uut $end
$var wire 1 ) clk $end
$var wire 1 0 flash_active $end
$var wire 1 * flash_mode $end
$var wire 1 + ped_request $end
$var wire 1 , reset $end
$var wire 1 - school_mode $end
$var wire 4 1 walk_seconds [3:0] $end
$var parameter 3 2 GREEN $end
$var parameter 4 3 NORMAL_MAIN_GREEN_TICKS $end
$var parameter 4 4 NORMAL_SIDE_GREEN_TICKS $end
$var parameter 4 5 NORMAL_WALK_SECONDS $end
$var parameter 3 6 OFF $end
$var parameter 3 7 RED $end
$var parameter 3 8 S0_MAIN_GREEN $end
$var parameter 3 9 S1_MAIN_YELLOW $end
$var parameter 3 : S2_SIDE_GREEN $end
$var parameter 3 ; S3_SIDE_YELLOW $end
$var parameter 3 < S4_WALK $end
$var parameter 4 = SCHOOL_MAIN_GREEN_TICKS $end
$var parameter 4 > SCHOOL_SIDE_GREEN_TICKS $end
$var parameter 4 ? SCHOOL_WALK_SECONDS $end
$var parameter 3 @ YELLOW $end
$var parameter 4 A YELLOW_TICKS $end
$var reg 4 B countdown [3:0] $end
$var reg 1 C flash_toggle $end
$var reg 4 D limit [3:0] $end
$var reg 3 E main_light [2:0] $end
$var reg 1 F ped_pending $end
$var reg 3 G side_light [2:0] $end
$var reg 3 H state [2:0] $end
$var reg 4 I timer [3:0] $end
$var reg 1 ! walk_light $end
$upscope $end
$scope task check $end
$var reg 1 J condition $end
$var reg 1024 K message [1023:0] $end
$upscope $end
$scope task check_safe $end
$upscope $end
$scope task expect_lights $end
$var reg 4 L expected_countdown [3:0] $end
$var reg 3 M expected_main [2:0] $end
$var reg 3 N expected_side [2:0] $end
$var reg 1 O expected_walk $end
$var reg 1024 P message [1023:0] $end
$upscope $end
$scope task wait_for_walk $end
$upscope $end
$scope task wait_tick $end
$upscope $end
$scope task wait_ticks $end
$var integer 32 Q n [31:0] $end
$upscope $end
$upscope $end
$enddefinitions $end
$comment Show the parameter values. $end
$dumpall
b11 A
b10 @
b1000 ?
b1010 >
b1000 =
b100 <
b11 ;
b10 :
b1 9
b0 8
b100 7
b0 6
b101 5
b1000 4
b1010 3
b1 2
b10 (
b100 '
b0 &
b1 %
$end
#0
$dumpvars
bx Q
bx P
xO
bx N
bx M
bx L
bx K
xJ
b0 I
b0 H
b100 G
0F
b1 E
b1010 D
1C
b0 B
b101 1
00
bx /
b0 .
0-
1,
0+
0*
0)
b0 $
b1 #
b100 "
0!
$end
#2000
0,
b11100100110010101110011011001010111010000100000011100100110010101110100011101010111001001101110011100110010000001110100011011110010000001110011011000010110011001100101001000000110110101100001011010010110111000100000011001110111001001100101011001010110111000100000011100110111010001100001011101000110010100100000011000110110111101110101011011100111010001100100011011110111011101101110 K
1J
b111001001100101011100110110010101110100001000000111001001100101011101000111010101110010011011100111001100100000011101000110111100100000011100110110000101100110011001010010000001101101011000010110100101101110001000000110011101110010011001010110010101101110001000000111001101110100011000010111010001100101 P
b0 L
0O
b100 N
b1 M
#5000
b1 I
1)
#6000
b0 /
b1001 Q
b1101110011011110111001001101101011000010110110000100000011011010110111101100100011001010010000001110011011101000110000101110010011101000111001100100000011101110110100101110100011010000010000001101101011000010110100101101110001000000110011101110010011001010110010101101110 P
b110111001101111011100100110110101100001011011000010000001101101011011110110010001100101001000000111001101110100011000010111001001110100011100110010000001110111011010010111010001101000001000000110110101100001011010010110111000100000011001110111001001100101011001010110111000100000011000110110111101110101011011100111010001100100011011110111011101101110 K
#10000
0)
#15000
b10 I
1)
#16000
b1 /
b1110111011000010110110001101011001000000110110001101001011001110110100001110100001000000110100101110011001000000110000101100011011101000110100101110110011001010010000001101111011011100110110001111001001000000111011101101000011001010110111000100000011000100110111101110100011010000010000001110010011011110110000101100100011100110010000001100001011100100110010100100000011100100110010101100100 K
#20000
0)
#25000
b11 I
1)
#26000
b10 /
b1110111011000010110110001101011001000000110110001101001011001110110100001110100001000000110100101110011001000000110000101100011011101000110100101110110011001010010000001101111011011100110110001111001001000000111011101101000011001010110111000100000011000100110111101110100011010000010000001110010011011110110000101100100011100110010000001100001011100100110010100100000011100100110010101100100 K
#30000
0)
#35000
b100 I
1)
#36000
b11 /
b1110111011000010110110001101011001000000110110001101001011001110110100001110100001000000110100101110011001000000110000101100011011101000110100101110110011001010010000001101111011011100110110001111001001000000111011101101000011001010110111000100000011000100110111101110100011010000010000001110010011011110110000101100100011100110010000001100001011100100110010100100000011100100110010101100100 K
#40000
0)
#45000
b101 I
1)
#46000
b100 /
b1110111011000010110110001101011001000000110110001101001011001110110100001110100001000000110100101110011001000000110000101100011011101000110100101110110011001010010000001101111011011100110110001111001001000000111011101101000011001010110111000100000011000100110111101110100011010000010000001110010011011110110000101100100011100110010000001100001011100100110010100100000011100100110010101100100 K
#50000
0)
#55000
b110 I
1)
#56000
b101 /
b1110111011000010110110001101011001000000110110001101001011001110110100001110100001000000110100101110011001000000110000101100011011101000110100101110110011001010010000001101111011011100110110001111001001000000111011101101000011001010110111000100000011000100110111101110100011010000010000001110010011011110110000101100100011100110010000001100001011100100110010100100000011100100110010101100100 K
#60000
0)
#65000
b111 I
1)
#66000
b110 /
b1110111011000010110110001101011001000000110110001101001011001110110100001110100001000000110100101110011001000000110000101100011011101000110100101110110011001010010000001101111011011100110110001111001001000000111011101101000011001010110111000100000011000100110111101110100011010000010000001110010011011110110000101100100011100110010000001100001011100100110010100100000011100100110010101100100 K
#70000
0)
#75000
b1000 I
1)
#76000
b111 /
b1110111011000010110110001101011001000000110110001101001011001110110100001110100001000000110100101110011001000000110000101100011011101000110100101110110011001010010000001101111011011100110110001111001001000000111011101101000011001010110111000100000011000100110111101110100011010000010000001110010011011110110000101100100011100110010000001100001011100100110010100100000011100100110010101100100 K
#80000
0)
#85000
b1001 I
1)
#86000
b1000 /
b1110111011000010110110001101011001000000110110001101001011001110110100001110100001000000110100101110011001000000110000101100011011101000110100101110110011001010010000001101111011011100110110001111001001000000111011101101000011001010110111000100000011000100110111101110100011010000010000001110010011011110110000101100100011100110010000001100001011100100110010100100000011100100110010101100100 K
#90000
0)
#95000
b11 D
b10 #
b10 E
b1 H
b0 I
1)
#96000
b11 Q
b1101110011011110111001001101101011000010110110000100000011011010110111101100100011001010010000001110010011001010110000101100011011010000110010101110011001000000110110101100001011010010110111000100000011110010110010101101100011011000110111101110111001000000110000101100110011101000110010101110010001000000011000100110000001000000111010001101001011000110110101101110011 P
b10 M
b0 /
b110111001101111011100100110110101100001011011000010000001101101011011110110010001100101001000000111001001100101011000010110001101101000011001010111001100100000011011010110000101101001011011100010000001111001011001010110110001101100011011110111011100100000011000010110011001110100011001010111001000100000001100010011000000100000011101000110100101100011011010110111001100100000011000110110111101110101011011100111010001100100011011110111011101101110 K
#100000
0)
#105000
b11 D
b1 I
1)
#106000
b1 /
b1110111011000010110110001101011001000000110110001101001011001110110100001110100001000000110100101110011001000000110000101100011011101000110100101110110011001010010000001101111011011100110110001111001001000000111011101101000011001010110111000100000011000100110111101110100011010000010000001110010011011110110000101100100011100110010000001100001011100100110010100100000011100100110010101100100 K
#110000
0)
#115000
b11 D
b10 I
1)
#116000
b10 /
b1110111011000010110110001101011001000000110110001101001011001110110100001110100001000000110100101110011001000000110000101100011011101000110100101110110011001010010000001101111011011100110110001111001001000000111011101101000011001010110111000100000011000100110111101110100011010000010000001110010011011110110000101100100011100110010000001100001011100100110010100100000011100100110010101100100 K
#120000
0)
#125000
b1 "
b1 G
b100 #
b100 E
b1000 D
b10 H
b0 I
1)
#126000
b1000 Q
b1101110011011110111001001101101011000010110110000100000011011010110111101100100011001010010000001110010011001010110000101100011011010000110010101110011001000000111001101101001011001000110010100100000011001110111001001100101011001010110111000100000011000010110011001110100011001010111001000100000011110010110010101101100011011000110111101110111 P
b1 N
b100 M
b0 /
b110111001101111011100100110110101100001011011000010000001101101011011110110010001100101001000000111001001100101011000010110001101101000011001010111001100100000011100110110100101100100011001010010000001100111011100100110010101100101011011100010000001100001011001100111010001100101011100100010000001111001011001010110110001101100011011110111011100100000011000110110111101110101011011100111010001100100011011110111011101101110 K
#130000
0)
#135000
b1000 D
b1 I
1)
#136000
b1 /
b1110111011000010110110001101011001000000110110001101001011001110110100001110100001000000110100101110011001000000110000101100011011101000110100101110110011001010010000001101111011011100110110001111001001000000111011101101000011001010110111000100000011000100110111101110100011010000010000001110010011011110110000101100100011100110010000001100001011100100110010100100000011100100110010101100100 K
#140000
0)
#145000
b1000 D
b10 I
1)
#146000
b10 /
b1110111011000010110110001101011001000000110110001101001011001110110100001110100001000000110100101110011001000000110000101100011011101000110100101110110011001010010000001101111011011100110110001111001001000000111011101101000011001010110111000100000011000100110111101110100011010000010000001110010011011110110000101100100011100110010000001100001011100100110010100100000011100100110010101100100 K
#150000
0)
#155000
b1000 D
b11 I
1)
#156000
b11 /
b1110111011000010110110001101011001000000110110001101001011001110110100001110100001000000110100101110011001000000110000101100011011101000110100101110110011001010010000001101111011011100110110001111001001000000111011101101000011001010110111000100000011000100110111101110100011010000010000001110010011011110110000101100100011100110010000001100001011100100110010100100000011100100110010101100100 K
#160000
0)
#165000
b1000 D
b100 I
1)
#166000
b100 /
b1110111011000010110110001101011001000000110110001101001011001110110100001110100001000000110100101110011001000000110000101100011011101000110100101110110011001010010000001101111011011100110110001111001001000000111011101101000011001010110111000100000011000100110111101110100011010000010000001110010011011110110000101100100011100110010000001100001011100100110010100100000011100100110010101100100 K
#170000
0)
#175000
b1000 D
b101 I
1)
#176000
b101 /
b1110111011000010110110001101011001000000110110001101001011001110110100001110100001000000110100101110011001000000110000101100011011101000110100101110110011001010010000001101111011011100110110001111001001000000111011101101000011001010110111000100000011000100110111101110100011010000010000001110010011011110110000101100100011100110010000001100001011100100110010100100000011100100110010101100100 K
#180000
0)
#185000
b1000 D
b110 I
1)
#186000
b110 /
b1110111011000010110110001101011001000000110110001101001011001110110100001110100001000000110100101110011001000000110000101100011011101000110100101110110011001010010000001101111011011100110110001111001001000000111011101101000011001010110111000100000011000100110111101110100011010000010000001110010011011110110000101100100011100110010000001100001011100100110010100100000011100100110010101100100 K
#190000
0)
#195000
b1000 D
b111 I
1)
#196000
b111 /
b1110111011000010110110001101011001000000110110001101001011001110110100001110100001000000110100101110011001000000110000101100011011101000110100101110110011001010010000001101111011011100110110001111001001000000111011101101000011001010110111000100000011000100110111101110100011010000010000001110010011011110110000101100100011100110010000001100001011100100110010100100000011100100110010101100100 K
#200000
0)
#205000
b10 "
b10 G
b11 D
b11 H
b0 I
1)
#206000
b11 Q
b1101110011011110111001001101101011000010110110000100000011011010110111101100100011001010010000001110011011010110110100101110000011100110010000001110111011000010110110001101011001000000111011101101001011101000110100001101111011101010111010000100000011100000110010101100100011001010111001101110100011100100110100101100001011011100010000001110010011001010111000101110101011001010111001101110100 P
b10 N
b0 /
b110111001101111011100100110110101100001011011000010000001101101011011110110010001100101001000000111001101101011011010010111000001110011001000000111011101100001011011000110101100100000011101110110100101110100011010000110111101110101011101000010000001110000011001010110010001100101011100110111010001110010011010010110000101101110001000000111001001100101011100010111010101100101011100110111010000100000011000110110111101110101011011100111010001100100011011110111011101101110 K
#210000
0)
#215000
b11 D
b1 I
1)
#216000
b1 /
b1110111011000010110110001101011001000000110110001101001011001110110100001110100001000000110100101110011001000000110000101100011011101000110100101110110011001010010000001101111011011100110110001111001001000000111011101101000011001010110111000100000011000100110111101110100011010000010000001110010011011110110000101100100011100110010000001100001011100100110010100100000011100100110010101100100 K
#220000
0)
#225000
b11 D
b10 I
1)
#226000
b10 /
b1110111011000010110110001101011001000000110110001101001011001110110100001110100001000000110100101110011001000000110000101100011011101000110100101110110011001010010000001101111011011100110110001111001001000000111011101101000011001010110111000100000011000100110111101110100011010000010000001110010011011110110000101100100011100110010000001100001011100100110010100100000011100100110010101100100 K
#230000
0)
#235000
b100 "
b100 G
b1 #
b1 E
b1010 D
b0 H
b0 I
1)
#236000
b1000 D
b1000 1
1-
b11011100110111101110010011011010110000101101100001000000110110101101111011001000110010100100000011100100110010101110100011101010111001001101110011100110010000001110100011011110010000001101101011000010110100101101110001000000110011101110010011001010110010101101110 P
b100 N
b1 M
b11 /
b1101110011011110111001001101101011000010110110000100000011011010110111101100100011001010010000001110010011001010111010001110101011100100110111001110011001000000111010001101111001000000110110101100001011010010110111000100000011001110111001001100101011001010110111000100000011000110110111101110101011011100111010001100100011011110111011101101110 K
#240000
0)
#245000
b1000 D
b1 I
1)
#246000
b0 /
b111 Q
b111001101100011011010000110111101101111011011000010000001101101011011110110010001100101001000000110110101100001011010010110111000100000011001110111001001100101011001010110111000100000011010010111001100100000011000010110001101110100011010010111011001100101 P
b11100110110001101101000011011110110111101101100001000000110110101101111011001000110010100100000011011010110000101101001011011100010000001100111011100100110010101100101011011100010000001101001011100110010000001100001011000110111010001101001011101100110010100100000011000110110111101110101011011100111010001100100011011110111011101101110 K
#250000
0)
#255000
b1000 D
b10 I
1)
#256000
b1 /
b1110111011000010110110001101011001000000110110001101001011001110110100001110100001000000110100101110011001000000110000101100011011101000110100101110110011001010010000001101111011011100110110001111001001000000111011101101000011001010110111000100000011000100110111101110100011010000010000001110010011011110110000101100100011100110010000001100001011100100110010100100000011100100110010101100100 K
#260000
0)
#265000
b1000 D
b11 I
1)
#266000
b10 /
b1110111011000010110110001101011001000000110110001101001011001110110100001110100001000000110100101110011001000000110000101100011011101000110100101110110011001010010000001101111011011100110110001111001001000000111011101101000011001010110111000100000011000100110111101110100011010000010000001110010011011110110000101100100011100110010000001100001011100100110010100100000011100100110010101100100 K
#270000
0)
#275000
b1000 D
b100 I
1)
#276000
b11 /
b1110111011000010110110001101011001000000110110001101001011001110110100001110100001000000110100101110011001000000110000101100011011101000110100101110110011001010010000001101111011011100110110001111001001000000111011101101000011001010110111000100000011000100110111101110100011010000010000001110010011011110110000101100100011100110010000001100001011100100110010100100000011100100110010101100100 K
#280000
0)
#285000
b1000 D
b101 I
1)
#286000
b100 /
b1110111011000010110110001101011001000000110110001101001011001110110100001110100001000000110100101110011001000000110000101100011011101000110100101110110011001010010000001101111011011100110110001111001001000000111011101101000011001010110111000100000011000100110111101110100011010000010000001110010011011110110000101100100011100110010000001100001011100100110010100100000011100100110010101100100 K
#290000
0)
#295000
b1000 D
b110 I
1)
#296000
b101 /
b1110111011000010110110001101011001000000110110001101001011001110110100001110100001000000110100101110011001000000110000101100011011101000110100101110110011001010010000001101111011011100110110001111001001000000111011101101000011001010110111000100000011000100110111101110100011010000010000001110010011011110110000101100100011100110010000001100001011100100110010100100000011100100110010101100100 K
#300000
0)
#305000
b1000 D
b111 I
1)
#306000
b110 /
b1110111011000010110110001101011001000000110110001101001011001110110100001110100001000000110100101110011001000000110000101100011011101000110100101110110011001010010000001101111011011100110110001111001001000000111011101101000011001010110111000100000011000100110111101110100011010000010000001110010011011110110000101100100011100110010000001100001011100100110010100100000011100100110010101100100 K
#310000
0)
#315000
b10 #
b10 E
b11 D
b1 H
b0 I
1)
#316000
b11 Q
b11100110110001101101000011011110110111101101100001000000110110101101111011001000110010100100000011100110110100001101111011100100111010001100101011011100111001100100000011011010110000101101001011011100010000001100111011100100110010101100101011011100010000001110100011011110010000000111000001000000111010001101001011000110110101101110011 P
b10 M
b0 /
b1110011011000110110100001101111011011110110110000100000011011010110111101100100011001010010000001110011011010000110111101110010011101000110010101101110011100110010000001101101011000010110100101101110001000000110011101110010011001010110010101101110001000000111010001101111001000000011100000100000011101000110100101100011011010110111001100100000011000110110111101110101011011100111010001100100011011110111011101101110 K
#320000
0)
#325000
b11 D
b1 I
1)
#326000
b1 /
b1110111011000010110110001101011001000000110110001101001011001110110100001110100001000000110100101110011001000000110000101100011011101000110100101110110011001010010000001101111011011100110110001111001001000000111011101101000011001010110111000100000011000100110111101110100011010000010000001110010011011110110000101100100011100110010000001100001011100100110010100100000011100100110010101100100 K
#330000
0)
#335000
b11 D
b10 I
1)
#336000
b10 /
b1110111011000010110110001101011001000000110110001101001011001110110100001110100001000000110100101110011001000000110000101100011011101000110100101110110011001010010000001101111011011100110110001111001001000000111011101101000011001010110111000100000011000100110111101110100011010000010000001110010011011110110000101100100011100110010000001100001011100100110010100100000011100100110010101100100 K
#340000
0)
#345000
b1 "
b1 G
b100 #
b100 E
b1010 D
b10 H
b0 I
1)
#346000
b1010 Q
b111001101100011011010000110111101101111011011000010000001101101011011110110010001100101001000000110010101101110011101000110010101110010011100110010000001110011011010010110010001100101001000000110011101110010011001010110010101101110 P
b1 N
b100 M
b0 /
b11100110110001101101000011011110110111101101100001000000110110101101111011001000110010100100000011001010110111001110100011001010111001001110011001000000111001101101001011001000110010100100000011001110111001001100101011001010110111000100000011000110110111101110101011011100111010001100100011011110111011101101110 K
#350000
0)
#355000
b1 I
1)
#356000
b1 /
b1110111011000010110110001101011001000000110110001101001011001110110100001110100001000000110100101110011001000000110000101100011011101000110100101110110011001010010000001101111011011100110110001111001001000000111011101101000011001010110111000100000011000100110111101110100011010000010000001110010011011110110000101100100011100110010000001100001011100100110010100100000011100100110010101100100 K
#360000
0)
#365000
b10 I
1)
#366000
b10 /
b1110111011000010110110001101011001000000110110001101001011001110110100001110100001000000110100101110011001000000110000101100011011101000110100101110110011001010010000001101111011011100110110001111001001000000111011101101000011001010110111000100000011000100110111101110100011010000010000001110010011011110110000101100100011100110010000001100001011100100110010100100000011100100110010101100100 K
#370000
0)
#375000
b11 I
1)
#376000
b11 /
b1110111011000010110110001101011001000000110110001101001011001110110100001110100001000000110100101110011001000000110000101100011011101000110100101110110011001010010000001101111011011100110110001111001001000000111011101101000011001010110111000100000011000100110111101110100011010000010000001110010011011110110000101100100011100110010000001100001011100100110010100100000011100100110010101100100 K
#380000
0)
#385000
b100 I
1)
#386000
b100 /
b1110111011000010110110001101011001000000110110001101001011001110110100001110100001000000110100101110011001000000110000101100011011101000110100101110110011001010010000001101111011011100110110001111001001000000111011101101000011001010110111000100000011000100110111101110100011010000010000001110010011011110110000101100100011100110010000001100001011100100110010100100000011100100110010101100100 K
#390000
0)
#395000
b101 I
1)
#396000
b101 /
b1110111011000010110110001101011001000000110110001101001011001110110100001110100001000000110100101110011001000000110000101100011011101000110100101110110011001010010000001101111011011100110110001111001001000000111011101101000011001010110111000100000011000100110111101110100011010000010000001110010011011110110000101100100011100110010000001100001011100100110010100100000011100100110010101100100 K
#400000
0)
#405000
b110 I
1)
#406000
b110 /
b1110111011000010110110001101011001000000110110001101001011001110110100001110100001000000110100101110011001000000110000101100011011101000110100101110110011001010010000001101111011011100110110001111001001000000111011101101000011001010110111000100000011000100110111101110100011010000010000001110010011011110110000101100100011100110010000001100001011100100110010100100000011100100110010101100100 K
#410000
0)
#415000
b111 I
1)
