lab06/lab06/latch_flipflop.v
`timescale 1ns / 1ps

module d_latch(
    input d,
    input enable,
    output reg q
);
    always @(*) begin
        if (enable) begin
            q = d;
        end
    end
endmodule

module d_flip_flop(
    input d,
    input clk,
    input reset_n,
    output reg q
);
    always @(posedge clk or negedge reset_n) begin
        if (!reset_n) begin
            q <= 1'b0;
        end else begin
            q <= d;
        end
    end
endmodule

lab06/lab06/tb_latch_flipflop.v
`timescale 1ns / 1ps

module tb_latch_flipflop;
    reg d;
    reg enable;
    reg clk;
    reg reset_n;
    wire q_latch;
    wire q_ff;

    d_latch latch0 (.d(d), .enable(enable), .q(q_latch));
    d_flip_flop ff0 (.d(d), .clk(clk), .reset_n(reset_n), .q(q_ff));

    initial begin
        clk = 1'b0;
        forever #5 clk = ~clk;
    end

    initial begin
        $dumpfile("lab06_latch_flipflop.vcd");
        $dumpvars(0, tb_latch_flipflop);

        d = 1'b0;
        enable = 1'b0;
        reset_n = 1'b0;
        #12;

        reset_n = 1'b1;
        enable = 1'b1;
        d = 1'b1;
        #12;

        d = 1'b0;
        #8;

        enable = 1'b0;
        d = 1'b1;
        #20;

        enable = 1'b1;
        d = 1'b0;
        #20;

        $finish;
    end
endmodule

lab06/lab06_latch_flipflop.vcd
$date
	Wed Jul 15 23:42:53 2026
$end
$version
	Icarus Verilog
$end
$timescale
	1ps
$end
$scope module tb_latch_flipflop $end
$var wire 1 ! q_latch $end
$var wire 1 " q_ff $end
$var reg 1 # clk $end
$var reg 1 $ d $end
$var reg 1 % enable $end
$var reg 1 & reset_n $end
$scope module ff0 $end
$var wire 1 # clk $end
$var wire 1 $ d $end
$var wire 1 & reset_n $end
$var reg 1 " q $end
$upscope $end
$scope module latch0 $end
$var wire 1 $ d $end
$var wire 1 % enable $end
$var reg 1 ! q $end
$upscope $end
$upscope $end
$enddefinitions $end
$comment Show the parameter values. $end
$dumpall
$end
#0
$dumpvars
0&
0%
0$
0#
0"
x!
$end
#5000
1#
#10000
0#
#12000
1!
1$
1%
1&
#15000
1"
1#
#20000
0#
#24000
0!
0$
#25000
0"
1#
#30000
0#
#32000
1$
0%
#35000
1"
1#
#40000
0#
#45000
1#
#50000
0#
#52000
0$
1%
#55000
0"
1#
